{
  "last_updated": "2024-12-22 23:59 IST",
  "movies": {
    "Pushpa: The Rule - Part 2 [2D | Hindi]": {
      "shows": 11887,
      "gross": 282264454,
      "sold": 1130062,
      "totalSeats": 2354296,
      "occupancy": 48,
      "details": [],
      "Chain_details": []
    },
    "Viduthalai Part - 2 [2D | Tamil]": {
      "shows": 3120,
      "gross": 62856160,
      "sold": 382033,
      "totalSeats": 1091523,
      "occupancy": 35,
      "details": [],
      "Chain_details": []
    },
    "Pushpa: The Rule - Part 2 [2D | Telugu]": {
      "shows": 2156,
      "gross": 59659826,
      "sold": 393573,
      "totalSeats": 803210,
      "occupancy": 49,
      "details": [],
      "Chain_details": []
    },
    "Mufasa: The Lion King [3D | Hindi]": {
      "shows": 3276,
      "gross": 59012068,
      "sold": 189679,
      "totalSeats": 632263,
      "occupancy": 30,
      "details": [],
      "Chain_details": []
    },
    "Mufasa: The Lion King [3D | English]": {
      "shows": 2305,
      "gross": 49407706,
      "sold": 142402,
      "totalSeats": 431521,
      "occupancy": 33,
      "details": [],
      "Chain_details": []
    },
    "Marco [2D | Malayalam]": {
      "shows": 1549,
      "gross": 47065703,
      "sold": 293028,
      "totalSeats": 361763,
      "occupancy": 81,
      "details": [],
      "Chain_details": []
    },
    "Ui [2D | Kannada]": {
      "shows": 935,
      "gross": 41163647,
      "sold": 185702,
      "totalSeats": 285695,
      "occupancy": 65,
      "details": [],
      "Chain_details": []
    },
    "Mufasa: The Lion King [3D | Telugu]": {
      "shows": 676,
      "gross": 24256439,
      "sold": 127965,
      "totalSeats": 228509,
      "occupancy": 56,
      "details": [],
      "Chain_details": []
    },
    "Mufasa: The Lion King [3D | Tamil]": {
      "shows": 987,
      "gross": 24008914,
      "sold": 151259,
      "totalSeats": 315123,
      "occupancy": 48,
      "details": [],
      "Chain_details": []
    },
    "Vanvaas [2D | Hindi]": {
      "shows": 1589,
      "gross": 13843611,
      "sold": 54221,
      "totalSeats": 225921,
      "occupancy": 24,
      "details": [],
      "Chain_details": []
    },
    "Rifle Club [2D | Malayalam]": {
      "shows": 917,
      "gross": 13661024,
      "sold": 81112,
      "totalSeats": 207979,
      "occupancy": 39,
      "details": [],
      "Chain_details": []
    },
    "Mufasa: The Lion King [IMAX 3D | English]": {
      "shows": 152,
      "gross": 13571914,
      "sold": 23834,
      "totalSeats": 45835,
      "occupancy": 52,
      "details": [],
      "Chain_details": []
    },
    "Bachhala Malli [2D | Telugu]": {
      "shows": 1240,
      "gross": 9156038,
      "sold": 78444,
      "totalSeats": 373543,
      "occupancy": 21,
      "details": [],
      "Chain_details": []
    },
    "Mufasa: The Lion King [2D | Hindi]": {
      "shows": 881,
      "gross": 9121261,
      "sold": 37944,
      "totalSeats": 158100,
      "occupancy": 24,
      "details": [],
      "Chain_details": []
    },
    "Khadaan [2D | Bengali]": {
      "shows": 275,
      "gross": 7840412,
      "sold": 43530,
      "totalSeats": 58824,
      "occupancy": 74,
      "details": [],
      "Chain_details": []
    },
    "Mufasa: The Lion King [2D | Telugu]": {
      "shows": 320,
      "gross": 7831526,
      "sold": 51851,
      "totalSeats": 110321,
      "occupancy": 47,
      "details": [],
      "Chain_details": []
    },
    "Ui [2D | Telugu]": {
      "shows": 618,
      "gross": 7719686,
      "sold": 57910,
      "totalSeats": 180969,
      "occupancy": 32,
      "details": [],
      "Chain_details": []
    },
    "Pushpa: The Rule - Part 2 [2D | Tamil]": {
      "shows": 439,
      "gross": 6950237,
      "sold": 48636,
      "totalSeats": 110536,
      "occupancy": 44,
      "details": [],
      "Chain_details": []
    },
    "Mufasa: The Lion King [4DX 3D | English]": {
      "shows": 131,
      "gross": 5173394,
      "sold": 8254,
      "totalSeats": 12506,
      "occupancy": 66,
      "details": [],
      "Chain_details": []
    },
    "Vidudala Part - 2 [2D | Telugu]": {
      "shows": 826,
      "gross": 5170703,
      "sold": 44921,
      "totalSeats": 236426,
      "occupancy": 19,
      "details": [],
      "Chain_details": []
    },
    "Moana 2 [3D | English]": {
      "shows": 174,
      "gross": 4452541,
      "sold": 13477,
      "totalSeats": 24957,
      "occupancy": 54,
      "details": [],
      "Chain_details": []
    },
    "Mufasa: The Lion King [IMAX 3D | Hindi]": {
      "shows": 42,
      "gross": 3992550,
      "sold": 6431,
      "totalSeats": 12367,
      "occupancy": 52,
      "details": [],
      "Chain_details": []
    },
    "Ed - Extra Decent [2D | Malayalam]": {
      "shows": 382,
      "gross": 3267429,
      "sold": 18685,
      "totalSeats": 66732,
      "occupancy": 28,
      "details": [],
      "Chain_details": []
    },
    "Mufasa: The Lion King [4DX 3D | Hindi]": {
      "shows": 65,
      "gross": 3156050,
      "sold": 4585,
      "totalSeats": 6550,
      "occupancy": 70,
      "details": [],
      "Chain_details": []
    },
    "Shontaan [2D | Bengali]": {
      "shows": 116,
      "gross": 2578998,
      "sold": 11389,
      "totalSeats": 22331,
      "occupancy": 51,
      "details": [],
      "Chain_details": []
    },
    "Mufasa: The Lion King [2D | English]": {
      "shows": 147,
      "gross": 2416525,
      "sold": 7388,
      "totalSeats": 21729,
      "occupancy": 34,
      "details": [],
      "Chain_details": []
    },
    "Mufasa: The Lion King [2D | Tamil]": {
      "shows": 101,
      "gross": 1988453,
      "sold": 12197,
      "totalSeats": 29749,
      "occupancy": 41,
      "details": [],
      "Chain_details": []
    },
    "Hashtag Tadev Lagnam [2D | Marathi]": {
      "shows": 106,
      "gross": 1648534,
      "sold": 6784,
      "totalSeats": 14748,
      "occupancy": 46,
      "details": [],
      "Chain_details": []
    },
    "Dharmarakshak Mahaveer Chhatrapati Sambhaji Maharaj [2D | Marathi]": {
      "shows": 56,
      "gross": 1369100,
      "sold": 5762,
      "totalSeats": 9146,
      "occupancy": 63,
      "details": [],
      "Chain_details": []
    },
    "Pushpa: The Rule - Part 2 [2D | Kannada]": {
      "shows": 102,
      "gross": 1168035,
      "sold": 7154,
      "totalSeats": 26496,
      "occupancy": 27,
      "details": [],
      "Chain_details": []
    },
    "The Sabarmati Report [2D | Hindi]": {
      "shows": 77,
      "gross": 1060732,
      "sold": 3758,
      "totalSeats": 9395,
      "occupancy": 40,
      "details": [],
      "Chain_details": []
    },
    "Darling Pyar Jhukta Nahi 2 [2D | Chattisgarhi]": {
      "shows": 79,
      "gross": 835480,
      "sold": 5971,
      "totalSeats": 17562,
      "occupancy": 34,
      "details": [],
      "Chain_details": []
    },
    "Sookshmadarshini [2D | Malayalam]": {
      "shows": 63,
      "gross": 811137,
      "sold": 4266,
      "totalSeats": 13761,
      "occupancy": 31,
      "details": [],
      "Chain_details": []
    },
    "Heretic [2D | English]": {
      "shows": 48,
      "gross": 798501,
      "sold": 2101,
      "totalSeats": 6179,
      "occupancy": 34,
      "details": [],
      "Chain_details": []
    },
    "Mufasa: The Lion King [ICE 3D | English]": {
      "shows": 15,
      "gross": 649820,
      "sold": 1252,
      "totalSeats": 2845,
      "occupancy": 44,
      "details": [],
      "Chain_details": []
    },
    "Marco [2D | Hindi]": {
      "shows": 81,
      "gross": 625390,
      "sold": 2614,
      "totalSeats": 9336,
      "occupancy": 28,
      "details": [],
      "Chain_details": []
    },
    "Shree Ganesha [2D | Marathi]": {
      "shows": 112,
      "gross": 549442,
      "sold": 2598,
      "totalSeats": 14433,
      "occupancy": 18,
      "details": [],
      "Chain_details": []
    },
    "Parab [2D | Odia]": {
      "shows": 86,
      "gross": 511938,
      "sold": 2476,
      "totalSeats": 13756,
      "occupancy": 18,
      "details": [],
      "Chain_details": []
    },
    "Miss You [2D | Tamil]": {
      "shows": 50,
      "gross": 495802,
      "sold": 3756,
      "totalSeats": 8536,
      "occupancy": 44,
      "details": [],
      "Chain_details": []
    },
    "Solo Leveling: Reawakening [2D | Japanese]": {
      "shows": 39,
      "gross": 491352,
      "sold": 2020,
      "totalSeats": 5611,
      "occupancy": 36,
      "details": [],
      "Chain_details": []
    },
    "All We Imagine As Light [2D | Malayalam]": {
      "shows": 16,
      "gross": 484510,
      "sold": 1095,
      "totalSeats": 2106,
      "occupancy": 52,
      "details": [],
      "Chain_details": []
    },
    "Chaalchitro - The Frame Fatale [2D | Bengali]": {
      "shows": 38,
      "gross": 481296,
      "sold": 2231,
      "totalSeats": 7968,
      "occupancy": 28,
      "details": [],
      "Chain_details": []
    },
    "Moana 2 [3D | Hindi]": {
      "shows": 38,
      "gross": 480110,
      "sold": 2000,
      "totalSeats": 5263,
      "occupancy": 38,
      "details": [],
      "Chain_details": []
    },
    "Once Upon A Time In Madras [2D | Tamil]": {
      "shows": 20,
      "gross": 443440,
      "sold": 3695,
      "totalSeats": 7698,
      "occupancy": 48,
      "details": [],
      "Chain_details": []
    },
    "Moana 2 [2D | English]": {
      "shows": 28,
      "gross": 411089,
      "sold": 1473,
      "totalSeats": 3876,
      "occupancy": 38,
      "details": [],
      "Chain_details": []
    },
    "5 No. Swapnomoy Lane [2D | Bengali]": {
      "shows": 56,
      "gross": 375187,
      "sold": 1958,
      "totalSeats": 10305,
      "occupancy": 19,
      "details": [],
      "Chain_details": []
    },
    "31st [2D | Gujarati]": {
      "shows": 101,
      "gross": 372150,
      "sold": 1792,
      "totalSeats": 9956,
      "occupancy": 18,
      "details": [],
      "Chain_details": []
    },
    "Ui [2D | Tamil]": {
      "shows": 75,
      "gross": 344516,
      "sold": 3154,
      "totalSeats": 14336,
      "occupancy": 22,
      "details": [],
      "Chain_details": []
    },
    "Mufasa: The Lion King [MX4D 3D | Hindi]": {
      "shows": 8,
      "gross": 332830,
      "sold": 582,
      "totalSeats": 856,
      "occupancy": 68,
      "details": [],
      "Chain_details": []
    },
    "Lucky Baskhar [2D | Telugu]": {
      "shows": 22,
      "gross": 331214,
      "sold": 2524,
      "totalSeats": 6642,
      "occupancy": 38,
      "details": [],
      "Chain_details": []
    },
    "Moana 2 [4DX 3D | English]": {
      "shows": 6,
      "gross": 304930,
      "sold": 528,
      "totalSeats": 587,
      "occupancy": 90,
      "details": [],
      "Chain_details": []
    },
    "Mufasa: The Lion King [MX4D 3D | English]": {
      "shows": 9,
      "gross": 292400,
      "sold": 474,
      "totalSeats": 912,
      "occupancy": 52,
      "details": [],
      "Chain_details": []
    },
    "Hello Mummy [2D | Malayalam]": {
      "shows": 26,
      "gross": 271221,
      "sold": 1380,
      "totalSeats": 3632,
      "occupancy": 38,
      "details": [],
      "Chain_details": []
    },
    "Vadda Ghar [2D | Punjabi]": {
      "shows": 118,
      "gross": 260580,
      "sold": 1236,
      "totalSeats": 13733,
      "occupancy": 9,
      "details": [],
      "Chain_details": []
    },
    "Pushpa: The Rule - Part 2 [2D | Malayalam]": {
      "shows": 33,
      "gross": 244757,
      "sold": 1363,
      "totalSeats": 6490,
      "occupancy": 21,
      "details": [],
      "Chain_details": []
    },
    "Ui [2D | Hindi]": {
      "shows": 48,
      "gross": 236240,
      "sold": 1111,
      "totalSeats": 9258,
      "occupancy": 12,
      "details": [],
      "Chain_details": []
    },
    "Outhouse [2D | Hindi]": {
      "shows": 22,
      "gross": 207004,
      "sold": 752,
      "totalSeats": 2149,
      "occupancy": 35,
      "details": [],
      "Chain_details": []
    },
    "Rrr - Behind And Beyond [2D | English]": {
      "shows": 34,
      "gross": 180246,
      "sold": 876,
      "totalSeats": 4171,
      "occupancy": 21,
      "details": [],
      "Chain_details": []
    },
    "Amaran [2D | Tamil]": {
      "shows": 29,
      "gross": 169829,
      "sold": 2738,
      "totalSeats": 5265,
      "occupancy": 52,
      "details": [],
      "Chain_details": []
    },
    "Haridasara Dinachari [2D | Kannada]": {
      "shows": 8,
      "gross": 163730,
      "sold": 648,
      "totalSeats": 1473,
      "occupancy": 44,
      "details": [],
      "Chain_details": []
    },
    "Moana 2 [2D | Hindi]": {
      "shows": 27,
      "gross": 156030,
      "sold": 637,
      "totalSeats": 2895,
      "occupancy": 22,
      "details": [],
      "Chain_details": []
    },
    "Gladiator Ii [2D | English]": {
      "shows": 5,
      "gross": 132110,
      "sold": 148,
      "totalSeats": 260,
      "occupancy": 57,
      "details": [],
      "Chain_details": []
    },
    "Bhairathi Ranagal [2D | Kannada]": {
      "shows": 19,
      "gross": 110690,
      "sold": 700,
      "totalSeats": 7000,
      "occupancy": 10,
      "details": [],
      "Chain_details": []
    },
    "Bhool Bhulaiyaa 3 [2D | Hindi]": {
      "shows": 13,
      "gross": 108670,
      "sold": 313,
      "totalSeats": 1204,
      "occupancy": 26,
      "details": [],
      "Chain_details": []
    },
    "Pushpa 2: The Rule [ICE | Hindi]": {
      "shows": 3,
      "gross": 92930,
      "sold": 249,
      "totalSeats": 553,
      "occupancy": 45,
      "details": [],
      "Chain_details": []
    },
    "The Wild Robot [3D | English]": {
      "shows": 7,
      "gross": 80900,
      "sold": 229,
      "totalSeats": 432,
      "occupancy": 53,
      "details": [],
      "Chain_details": []
    },
    "Soodhu Kavvum 2 [2D | Tamil]": {
      "shows": 14,
      "gross": 67100,
      "sold": 591,
      "totalSeats": 2686,
      "occupancy": 22,
      "details": [],
      "Chain_details": []
    },
    "Jammu 86 Gangwar [2D | Punjabi]": {
      "shows": 9,
      "gross": 64830,
      "sold": 230,
      "totalSeats": 1278,
      "occupancy": 18,
      "details": [],
      "Chain_details": []
    },
    "Peg, Thrill Par Thrill [2D | Gujarati]": {
      "shows": 21,
      "gross": 62760,
      "sold": 264,
      "totalSeats": 1886,
      "occupancy": 14,
      "details": [],
      "Chain_details": []
    },
    "Pani [2D | Telugu]": {
      "shows": 4,
      "gross": 62200,
      "sold": 1004,
      "totalSeats": 1004,
      "occupancy": 100,
      "details": [],
      "Chain_details": []
    },
    "Miss You [2D | Telugu]": {
      "shows": 12,
      "gross": 59266,
      "sold": 461,
      "totalSeats": 4610,
      "occupancy": 10,
      "details": [],
      "Chain_details": []
    },
    "Adiparvam [2D | Telugu]": {
      "shows": 3,
      "gross": 58440,
      "sold": 1056,
      "totalSeats": 1760,
      "occupancy": 60,
      "details": [],
      "Chain_details": []
    },
    "Rudhiram [2D | Malayalam]": {
      "shows": 12,
      "gross": 53370,
      "sold": 258,
      "totalSeats": 1173,
      "occupancy": 22,
      "details": [],
      "Chain_details": []
    },
    "Pushpa 2: The Rule [3D | Telugu]": {
      "shows": 1,
      "gross": 53313,
      "sold": 249,
      "totalSeats": 262,
      "occupancy": 95,
      "details": [],
      "Chain_details": []
    },
    "Wicked [3D | English]": {
      "shows": 2,
      "gross": 51100,
      "sold": 53,
      "totalSeats": 95,
      "occupancy": 56,
      "details": [],
      "Chain_details": []
    },
    "The Lord Of The Rings: The War Of The Rohirrim [2D | English]": {
      "shows": 10,
      "gross": 47350,
      "sold": 208,
      "totalSeats": 1224,
      "occupancy": 17,
      "details": [],
      "Chain_details": []
    },
    "Bharga [2D | Bengali]": {
      "shows": 3,
      "gross": 45240,
      "sold": 660,
      "totalSeats": 3300,
      "occupancy": 20,
      "details": [],
      "Chain_details": []
    },
    "Bohurupi [2D | Bengali]": {
      "shows": 3,
      "gross": 44470,
      "sold": 240,
      "totalSeats": 533,
      "occupancy": 45,
      "details": [],
      "Chain_details": []
    },
    "C202 [2D | Telugu]": {
      "shows": 4,
      "gross": 41120,
      "sold": 508,
      "totalSeats": 1494,
      "occupancy": 34,
      "details": [],
      "Chain_details": []
    },
    "Moana 2 [ICE 3D | English]": {
      "shows": 1,
      "gross": 38970,
      "sold": 61,
      "totalSeats": 136,
      "occupancy": 45,
      "details": [],
      "Chain_details": []
    },
    "Amaran [2D | Telugu]": {
      "shows": 18,
      "gross": 38425,
      "sold": 315,
      "totalSeats": 4500,
      "occupancy": 7,
      "details": [],
      "Chain_details": []
    },
    "Sorgavaasal [2D | Tamil]": {
      "shows": 9,
      "gross": 33689,
      "sold": 278,
      "totalSeats": 1030,
      "occupancy": 27,
      "details": [],
      "Chain_details": []
    },
    "Anand Sreebala [2D | Malayalam]": {
      "shows": 3,
      "gross": 32200,
      "sold": 322,
      "totalSeats": 920,
      "occupancy": 35,
      "details": [],
      "Chain_details": []
    },
    "Aaram Arvindswamy [2D | Kannada]": {
      "shows": 2,
      "gross": 27530,
      "sold": 124,
      "totalSeats": 400,
      "occupancy": 31,
      "details": [],
      "Chain_details": []
    },
    "Wicked [2D | English]": {
      "shows": 3,
      "gross": 23130,
      "sold": 78,
      "totalSeats": 223,
      "occupancy": 35,
      "details": [],
      "Chain_details": []
    },
    "The Wild Robot [2D | English]": {
      "shows": 3,
      "gross": 20010,
      "sold": 116,
      "totalSeats": 258,
      "occupancy": 45,
      "details": [],
      "Chain_details": []
    },
    "Lucky Baskhar [2D | Kannada]": {
      "shows": 4,
      "gross": 17450,
      "sold": 134,
      "totalSeats": 2680,
      "occupancy": 5,
      "details": [],
      "Chain_details": []
    },
    "Amaran [2D | Hindi]": {
      "shows": 5,
      "gross": 13500,
      "sold": 56,
      "totalSeats": 160,
      "occupancy": 35,
      "details": [],
      "Chain_details": []
    },
    "Mufasa: The Lion King [ICE | English]": {
      "shows": 1,
      "gross": 10580,
      "sold": 21,
      "totalSeats": 131,
      "occupancy": 16,
      "details": [],
      "Chain_details": []
    },
    "Devara - Part 1 [2D | Telugu]": {
      "shows": 20,
      "gross": 10270,
      "sold": 1562,
      "totalSeats": 5579,
      "occupancy": 28,
      "details": [],
      "Chain_details": []
    },
    "Solo Leveling: Reawakening [2D | English]": {
      "shows": 1,
      "gross": 9480,
      "sold": 50,
      "totalSeats": 67,
      "occupancy": 75,
      "details": [],
      "Chain_details": []
    },
    "Naam [2D | Hindi]": {
      "shows": 8,
      "gross": 8500,
      "sold": 58,
      "totalSeats": 1933,
      "occupancy": 3,
      "details": [],
      "Chain_details": []
    },
    "Ajab Raat Ni Gajab Vaat [2D | Gujarati]": {
      "shows": 4,
      "gross": 8380,
      "sold": 57,
      "totalSeats": 219,
      "occupancy": 26,
      "details": [],
      "Chain_details": []
    },
    "Kung Fu Panda 4 [2D | English]": {
      "shows": 2,
      "gross": 8250,
      "sold": 45,
      "totalSeats": 145,
      "occupancy": 31,
      "details": [],
      "Chain_details": []
    },
    "Zebra [2D | Telugu]": {
      "shows": 12,
      "gross": 7140,
      "sold": 102,
      "totalSeats": 600,
      "occupancy": 17,
      "details": [],
      "Chain_details": []
    },
    "The Wild Robot [3D | Hindi]": {
      "shows": 1,
      "gross": 6680,
      "sold": 18,
      "totalSeats": 78,
      "occupancy": 23,
      "details": [],
      "Chain_details": []
    },
    "Singham Again [2D | Hindi]": {
      "shows": 5,
      "gross": 6670,
      "sold": 47,
      "totalSeats": 783,
      "occupancy": 6,
      "details": [],
      "Chain_details": []
    },
    "Dilwale Dulhania Le Jayenge [2D | Hindi]": {
      "shows": 1,
      "gross": 6060,
      "sold": 155,
      "totalSeats": 1033,
      "occupancy": 15,
      "details": [],
      "Chain_details": []
    },
    "Naa Ninna Bidalare [2D | Kannada]": {
      "shows": 1,
      "gross": 5760,
      "sold": 48,
      "totalSeats": 267,
      "occupancy": 18,
      "details": [],
      "Chain_details": []
    },
    "Mufasa: The Lion King [IMAX 2D | English]": {
      "shows": 1,
      "gross": 5730,
      "sold": 13,
      "totalSeats": 260,
      "occupancy": 5,
      "details": [],
      "Chain_details": []
    },
    "Despicable Me 4 [2D | English]": {
      "shows": 1,
      "gross": 5250,
      "sold": 35,
      "totalSeats": 54,
      "occupancy": 65,
      "details": [],
      "Chain_details": []
    },
    "Laila Majnu [2D | Hindi]": {
      "shows": 1,
      "gross": 4368,
      "sold": 39,
      "totalSeats": 170,
      "occupancy": 23,
      "details": [],
      "Chain_details": []
    },
    "Iyyappan Thunaiyiruppan [2D | Tamil]": {
      "shows": 6,
      "gross": 4100,
      "sold": 54,
      "totalSeats": 2700,
      "occupancy": 2,
      "details": [],
      "Chain_details": []
    },
    "Oxygen [2D | Odia]": {
      "shows": 1,
      "gross": 3220,
      "sold": 14,
      "totalSeats": 127,
      "occupancy": 11,
      "details": [],
      "Chain_details": []
    },
    "Ameena [2D | Hindi]": {
      "shows": 1,
      "gross": 3000,
      "sold": 30,
      "totalSeats": 63,
      "occupancy": 48,
      "details": [],
      "Chain_details": []
    },
    "Amaran [2D | Kannada]": {
      "shows": 1,
      "gross": 2700,
      "sold": 18,
      "totalSeats": 200,
      "occupancy": 9,
      "details": [],
      "Chain_details": []
    },
    "Love Lagna Locha [2D | Marathi]": {
      "shows": 4,
      "gross": 2520,
      "sold": 36,
      "totalSeats": 900,
      "occupancy": 4,
      "details": [],
      "Chain_details": []
    },
    "Kanguva [2D | Hindi]": {
      "shows": 1,
      "gross": 1800,
      "sold": 12,
      "totalSeats": 52,
      "occupancy": 23,
      "details": [],
      "Chain_details": []
    },
    "Thamate [2D | Kannada]": {
      "shows": 2,
      "gross": 1300,
      "sold": 13,
      "totalSeats": 325,
      "occupancy": 4,
      "details": [],
      "Chain_details": []
    },
    "Kalki 2898 Ad [2D | Telugu]": {
      "shows": 4,
      "gross": 1250,
      "sold": 9,
      "totalSeats": 900,
      "occupancy": 1,
      "details": [],
      "Chain_details": []
    },
    "Mechanic Rocky [2D | Telugu]": {
      "shows": 1,
      "gross": 440,
      "sold": 4,
      "totalSeats": 200,
      "occupancy": 2,
      "details": [],
      "Chain_details": []
    },
    "The Rabbit House [2D | Hindi]": {
      "shows": 1,
      "gross": 0,
      "sold": 0,
      "totalSeats": 0,
      "occupancy": 100,
      "details": [],
      "Chain_details": []
    },
    "Sasan [2D | Gujarati]": {
      "shows": 1,
      "gross": 0,
      "sold": 0,
      "totalSeats": 0,
      "occupancy": 0,
      "details": [],
      "Chain_details": []
    },
    "31st December [2D | Gujarati]": {
      "shows": 1,
      "gross": 0,
      "sold": 0,
      "totalSeats": 0,
      "occupancy": 100,
      "details": [],
      "Chain_details": []
    },
    "Marco [2D | Telugu]": {
      "shows": 1,
      "gross": 0,
      "sold": 0,
      "totalSeats": 0,
      "occupancy": 100,
      "details": [],
      "Chain_details": []
    },
    "Despicable Me 4 [3D | English]": {
      "shows": 1,
      "gross": 0,
      "sold": 0,
      "totalSeats": 0,
      "occupancy": 100,
      "details": [],
      "Chain_details": []
    },
    "Mura [2D | Malayalam]": {
      "shows": 2,
      "gross": 0,
      "sold": 0,
      "totalSeats": 0,
      "occupancy": 100,
      "details": [],
      "Chain_details": []
    },
    "Iru Manasu [2D | Tamil]": {
      "shows": 2,
      "gross": 0,
      "sold": 0,
      "totalSeats": 0,
      "occupancy": 0,
      "details": [],
      "Chain_details": []
    },
    "Udan Chhoo [2D | Gujarati]": {
      "shows": 1,
      "gross": 0,
      "sold": 0,
      "totalSeats": 0,
      "occupancy": 0,
      "details": [],
      "Chain_details": []
    },
    "Pushpa 2: The Rule [3D | Hindi]": {
      "shows": 1,
      "gross": 0,
      "sold": 0,
      "totalSeats": 0,
      "occupancy": 100,
      "details": [],
      "Chain_details": []
    },
    "Bheema [2D | Kannada]": {
      "shows": 3,
      "gross": 0,
      "sold": 0,
      "totalSeats": 0,
      "occupancy": 0,
      "details": [],
      "Chain_details": []
    }
  }
}